Metadata-Version: 1.1
Name: GTsegments
Version: 0.22
Summary: UNKNOWN
Home-page: UNKNOWN
Author: Philippe Bordron
Author-email: philippe.bordron+GTsegments@gmail.com
License: LGPL
Keywords: bioinformatics Genome Genomic Transcriptome Trancriptomic GTsegments
Platform: UNKNOWN
Classifier: Development Status :: 4 - Beta
Classifier: License :: OSI Approved :: GNU Lesser General Public License v3 (LGPLv3)
Classifier: Programming Language :: Python :: 2.7
Classifier: Programming Language :: Python :: 3
Classifier: Topic :: Software Development :: Libraries :: Python Modules
Classifier: Operating System :: OS Independent
